s3db
